AUTHORS.rst
CONTRIBUTING.rst
HISTORY.rst
LICENSE
MANIFEST.in
README.rst
setup.cfg
setup.py
docs/Makefile
docs/authors.rst
docs/citation.rst
docs/conf.py
docs/contributing.rst
docs/history.rst
docs/index.rst
docs/installation.rst
docs/make.bat
docs/modules.rst
docs/onboarding.rst
docs/readme.rst
docs/slsim.Deflectors.DeflectorPopulation.rst
docs/slsim.Deflectors.DeflectorTypes.rst
docs/slsim.Deflectors.MassLightConnection.rst
docs/slsim.Deflectors.rst
docs/slsim.FalsePositives.rst
docs/slsim.Halos.rst
docs/slsim.ImageSimulation.rst
docs/slsim.LOS.rst
docs/slsim.Lenses.rst
docs/slsim.LsstSciencePipeline.rst
docs/slsim.Microlensing.rst
docs/slsim.Microlensing.source_morphology.rst
docs/slsim.Pipelines.rst
docs/slsim.Plots.rst
docs/slsim.Sources.SourceCatalogues.QuasarCatalog.rst
docs/slsim.Sources.SourceCatalogues.SupernovaeCatalog.rst
docs/slsim.Sources.SourceCatalogues.rst
docs/slsim.Sources.SourcePopulation.rst
docs/slsim.Sources.SourceTypes.rst
docs/slsim.Sources.SourceVariability.rst
docs/slsim.Sources.Supernovae.rst
docs/slsim.Sources.rst
docs/slsim.Util.ParamDistributions.rst
docs/slsim.Util.rst
docs/slsim.rst
docs/tutorial.rst
slsim/__init__.py
slsim.egg-info/PKG-INFO
slsim.egg-info/SOURCES.txt
slsim.egg-info/dependency_links.txt
slsim.egg-info/not-zip-safe
slsim.egg-info/requires.txt
slsim.egg-info/top_level.txt
slsim/Deflectors/__init__.py
slsim/Deflectors/deflector.py
slsim/Deflectors/DeflectorPopulation/__init__.py
slsim/Deflectors/DeflectorPopulation/all_lens_galaxies.py
slsim/Deflectors/DeflectorPopulation/cluster_deflectors.py
slsim/Deflectors/DeflectorPopulation/compound_lens_halos_galaxies.py
slsim/Deflectors/DeflectorPopulation/deflectors_base.py
slsim/Deflectors/DeflectorPopulation/elliptical_lens_galaxies.py
slsim/Deflectors/DeflectorTypes/__init__.py
slsim/Deflectors/DeflectorTypes/deflector_base.py
slsim/Deflectors/DeflectorTypes/epl.py
slsim/Deflectors/DeflectorTypes/epl_sersic.py
slsim/Deflectors/DeflectorTypes/nfw_cluster.py
slsim/Deflectors/DeflectorTypes/nfw_hernquist.py
slsim/Deflectors/MassLightConnection/__init__.py
slsim/Deflectors/MassLightConnection/galaxy_population.py
