Metadata-Version: 2.1
Name: slsim
Version: 0.1.1
Summary: LSST strong lensing simulation pipeline
Home-page: https://github.com/LSST-strong-lensing/slsim
Author: DESC/SLSC
Author-email: sibirrer@gmail.com
License: MIT license
Keywords: slsim
Classifier: Development Status :: 4 - Beta
Classifier: Intended Audience :: Developers
Classifier: License :: OSI Approved :: MIT License
Classifier: Natural Language :: English
Classifier: Programming Language :: Python :: 3
Classifier: Programming Language :: Python :: 3.6
Classifier: Programming Language :: Python :: 3.7
Classifier: Programming Language :: Python :: 3.8
Requires-Python: >=3.6
License-File: LICENSE
License-File: AUTHORS.rst
